setup.py
cratis_base/__init__.py
cratis_base/features.py
django_cratis_base.egg-info/PKG-INFO
django_cratis_base.egg-info/SOURCES.txt
django_cratis_base.egg-info/dependency_links.txt
django_cratis_base.egg-info/requires.txt
django_cratis_base.egg-info/top_level.txt