Metadata-Version: 1.0
Name: django-cratis-base
Version: 0.1.5
Summary: Django-cratis is a way to group together django applications, so they form reusable features.
Home-page: UNKNOWN
Author: Alex Rudakov
Author-email: ribozz@gmail.com
License: MIT License
Platform: UNKNOWN
